odoo/addons/agreement_helpdesk_mgmt/README.rst
odoo/addons/agreement_helpdesk_mgmt/__init__.py
odoo/addons/agreement_helpdesk_mgmt/__manifest__.py
odoo/addons/agreement_helpdesk_mgmt/i18n/agreement_helpdesk_mgmt.pot
odoo/addons/agreement_helpdesk_mgmt/i18n/it.po
odoo/addons/agreement_helpdesk_mgmt/i18n/sv.po
odoo/addons/agreement_helpdesk_mgmt/models/__init__.py
odoo/addons/agreement_helpdesk_mgmt/models/agreement.py
odoo/addons/agreement_helpdesk_mgmt/models/helpdesk_ticket.py
odoo/addons/agreement_helpdesk_mgmt/readme/CONTRIBUTORS.md
odoo/addons/agreement_helpdesk_mgmt/readme/CREDITS.md
odoo/addons/agreement_helpdesk_mgmt/readme/DESCRIPTION.md
odoo/addons/agreement_helpdesk_mgmt/readme/USAGE.md
odoo/addons/agreement_helpdesk_mgmt/static/description/banner.png
odoo/addons/agreement_helpdesk_mgmt/static/description/icon.png
odoo/addons/agreement_helpdesk_mgmt/static/description/index.html
odoo/addons/agreement_helpdesk_mgmt/tests/__init__.py
odoo/addons/agreement_helpdesk_mgmt/tests/test_agreement_helpdesk_mgmt.py
odoo/addons/agreement_helpdesk_mgmt/views/agreement.xml
odoo/addons/agreement_helpdesk_mgmt/views/helpdesk_ticket.xml
odoo_addon_agreement_helpdesk_mgmt-18.0.1.0.0.7.dist-info/METADATA
odoo_addon_agreement_helpdesk_mgmt-18.0.1.0.0.7.dist-info/WHEEL
odoo_addon_agreement_helpdesk_mgmt-18.0.1.0.0.7.dist-info/top_level.txt
odoo_addon_agreement_helpdesk_mgmt-18.0.1.0.0.7.dist-info/RECORD
